tg4perfetto/__init__.py
tg4perfetto/_core.py
tg4perfetto/_profile.py
tg4perfetto/_tgen.py
tg4perfetto/example.py
tg4perfetto/example_profile.py
tg4perfetto/perfetto_trace_pb2.py
tg4perfetto-0.0.4.dist-info/METADATA
tg4perfetto-0.0.4.dist-info/WHEEL
tg4perfetto-0.0.4.dist-info/licenses/LICENSE
tg4perfetto-0.0.4.dist-info/RECORD
