Metadata-Version: 2.1
Name: tg4perfetto
Version: 0.0.4
Summary: A python project 
Project-URL: Homepage, https://github.com/ihavnoid/tg4perfetto
Project-URL: Bug Tracker, https://github.com/ihavnoid/tg4perfetto/issues
Author-email: Junhee Yoo <ihavnoid@yahoo.com>
License:                                  Apache License
Classifier: License :: OSI Approved :: Apache Software License
Classifier: Operating System :: OS Independent
Classifier: Programming Language :: Python :: 3
Requires-Python: >=3.7
